nway-4.7.0.data/scripts/nway-calibrate-cutoff.py
nway-4.7.0.data/scripts/nway-create-fake-catalogue.py
nway-4.7.0.data/scripts/nway-create-shifted-catalogue.py
nway-4.7.0.data/scripts/nway-explain.py
nway-4.7.0.data/scripts/nway-write-header.py
nway-4.7.0.data/scripts/nway.py
nwaylib/__init__.py
nwaylib/bayesdistance.py
nwaylib/checkupdates.py
nwaylib/fastskymatch.py
nwaylib/logger.py
nwaylib/magnitudeweights.py
nwaylib/progress.py
nway-4.7.0.dist-info/COPYING
nway-4.7.0.dist-info/LICENSE
nway-4.7.0.dist-info/METADATA
nway-4.7.0.dist-info/WHEEL
nway-4.7.0.dist-info/top_level.txt
nway-4.7.0.dist-info/RECORD
