Metadata-Version: 2.2
Name: nway
Version: 4.7.0
Summary: Probabilistic Cross-Identification of Astronomical Sources
Author-email: Johannes Buchner <johannes.buchner.acad@gmx.com>
License: 
Project-URL: Repository, https://github.com/JohannesBuchner/nway/
Project-URL: homepage, https://github.com/JohannesBuchner/nway/
Project-URL: documentation, https://raw.githubusercontent.com/JohannesBuchner/nway/master/doc/nway-manual.pdf
Requires-Python: >=3.8
License-File: LICENSE
License-File: COPYING
Requires-Dist: numpy
Requires-Dist: scipy
Requires-Dist: astropy
Requires-Dist: tqdm
Requires-Dist: healpy
Requires-Dist: joblib
Requires-Dist: matplotlib
Requires-Dist: pandas
Provides-Extra: test
Requires-Dist: pytest; extra == "test"
